odoo/addons/ssi_psychology_operating_unit/README.rst
odoo/addons/ssi_psychology_operating_unit/__init__.py
odoo/addons/ssi_psychology_operating_unit/__manifest__.py
odoo/addons/ssi_psychology_operating_unit/static/description/icon.png
odoo14_addon_ssi_psychology_operating_unit-14.0.2.1.0.dist-info/METADATA
odoo14_addon_ssi_psychology_operating_unit-14.0.2.1.0.dist-info/WHEEL
odoo14_addon_ssi_psychology_operating_unit-14.0.2.1.0.dist-info/top_level.txt
odoo14_addon_ssi_psychology_operating_unit-14.0.2.1.0.dist-info/RECORD
